jupyter_admin/__init__.py
jupyter_admin/_version.py
jupyter_admin/handlers.py
jupyter_admin/labextension/build_log.json
jupyter_admin/labextension/package.json
jupyter_admin/labextension/schemas/@datalayer/datalayer/package.json.orig
jupyter_admin/labextension/schemas/@datalayer/datalayer/plugin.json
jupyter_admin/labextension/static/design_icons_lib_index_js.be93483f00a96ee67977.js
jupyter_admin/labextension/static/design_icons_lib_index_js.be93483f00a96ee67977.js.map
jupyter_admin/labextension/static/lib_index_js.6c7e7c1674dff26c78c0.js
jupyter_admin/labextension/static/lib_index_js.6c7e7c1674dff26c78c0.js.map
jupyter_admin/labextension/static/remoteEntry.39926d768d35e45ef493.js
jupyter_admin/labextension/static/remoteEntry.39926d768d35e45ef493.js.map
jupyter_admin/labextension/static/style.js
jupyter_admin/labextension/static/style_index_js.7efdc787a3382c975f65.js
jupyter_admin/labextension/static/style_index_js.7efdc787a3382c975f65.js.map
jupyter_admin/labextension/static/vendors-node_modules_css-loader_dist_runtime_api_js-node_modules_css-loader_dist_runtime_cssW-72eba1.84d2763c7dacb5e8a254.js
jupyter_admin/labextension/static/vendors-node_modules_css-loader_dist_runtime_api_js-node_modules_css-loader_dist_runtime_cssW-72eba1.84d2763c7dacb5e8a254.js.map
jupyter_admin/labextension/static/vendors-node_modules_primer_octicons-react_dist_index_esm_js.e9168892a5ebfdad072e.js
jupyter_admin/labextension/static/vendors-node_modules_primer_octicons-react_dist_index_esm_js.e9168892a5ebfdad072e.js.map
jupyter_admin/labextension/static/vendors-node_modules_primer_react_lib-esm_ActionList_index_js-node_modules_primer_react_lib-e-ade24b.f7d47b4f14db7c7f9a18.js
jupyter_admin/labextension/static/vendors-node_modules_primer_react_lib-esm_ActionList_index_js-node_modules_primer_react_lib-e-ade24b.f7d47b4f14db7c7f9a18.js.map
jupyter_admin-0.0.2.dist-info/METADATA
jupyter_admin-0.0.2.dist-info/WHEEL
jupyter_admin-0.0.2.dist-info/licenses/LICENSE
jupyter_admin-0.0.2.dist-info/RECORD
